itusm2117/__init__.py
itusm2117/_internal.py
itusm2117/_schema.py
itusm2117/read.py
itusm2117/write.py
itusm2117-0.0.1.dist-info/LICENSE
itusm2117-0.0.1.dist-info/METADATA
itusm2117-0.0.1.dist-info/WHEEL
itusm2117-0.0.1.dist-info/top_level.txt
itusm2117-0.0.1.dist-info/RECORD
