Metadata-Version: 2.1
Name: itusm2117
Version: 0.0.1
Summary: ITU-R SM.2117-0 Python Library
Home-page: https://github.com/KeyBridge/lib-itu-sm2117
Author: André Teixeira dos Santos
Author-email: andre.santos@keybridgewireless.com
Project-URL: Bug Tracker, https://github.com/KeyBridge/lib-itu-sm2117/issues
Classifier: Programming Language :: Python :: 3
Classifier: License :: OSI Approved :: MIT License
Classifier: Operating System :: OS Independent
Requires-Python: >=3.6
License-File: LICENSE
Requires-Dist: numpy (>=1.19.5)
Requires-Dist: h5py (>=3.1.0)
Requires-Dist: Cerberus (>=1.3.4)
Requires-Dist: python-dateutil (>=2.8.2)
